pypiparser/__init__.py
pypiparser/packageindex.py
pypiparser-0.2.4.dist-info/LICENSE
pypiparser-0.2.4.dist-info/METADATA
pypiparser-0.2.4.dist-info/WHEEL
pypiparser-0.2.4.dist-info/top_level.txt
pypiparser-0.2.4.dist-info/RECORD
