Metadata-Version: 2.1
Name: pypiparser
Version: 0.2.4
Summary: Simple Python Package Index Parser
Home-page: https://github.com/timlehr/pypiparser
Author: Tim Lehr
Author-email: contact@timlehr.com
License: MIT
Keywords: pypi,parser,packaging,simple,pip
Platform: UNKNOWN
Classifier: Development Status :: 3 - Alpha
Classifier: Programming Language :: Python :: 2.7
Classifier: Programming Language :: Python :: 3.6
Requires-Dist: beautifulsoup4
Requires-Dist: requests
